ChangeLog.rst
LICENSE
MANIFEST.in
README.rst
setup.py
conf/attributes.yml
conf/ldapcherry.ini
conf/roles.yml
docs/Makefile
docs/README.rst
docs/backend_api.rst
docs/backends.rst
docs/changelog.rst
docs/conf.py
docs/deploy.rst
docs/docs_requirements.txt
docs/external_plugins.rst
docs/forkme.rst
docs/full_configuration.rst
docs/goodies.rst
docs/index.rst
docs/install.rst
docs/make.bat
docs/ppolicy_api.rst
docs/screenshots.rst
docs/assets/banner.css
docs/assets/basic.css
docs/assets/cherrypy.jpg
docs/assets/cherrypy.png
docs/assets/favicon.png
docs/assets/logo.png
docs/assets/nature.css
docs/assets/pygments.css
docs/assets/python-logo.png
docs/assets/python-powered.png
docs/assets/sc/2015-07-06-093051_1438x1064_scrot.png
docs/assets/sc/2015-07-06-093130_1438x1064_scrot.png
docs/assets/sc/2015-07-06-093147_1438x1064_scrot.png
docs/assets/sc/2015-07-06-093152_1438x1064_scrot.png
docs/assets/sc/2015-07-06-093215_1438x1064_scrot.png
docs/assets/sc/2015-07-06-093234_1438x1064_scrot.png
docs/docs/assets/banner.css
docs/docs/assets/basic.css
docs/docs/assets/cherrypy.jpg
docs/docs/assets/cherrypy.png
docs/docs/assets/favicon.png
docs/docs/assets/logo.png
docs/docs/assets/nature.css
docs/docs/assets/pygments.css
docs/docs/assets/python-logo.png
docs/docs/assets/python-powered.png
docs/docs/assets/sc/2015-07-06-093051_1438x1064_scrot.png
docs/docs/assets/sc/2015-07-06-093130_1438x1064_scrot.png
docs/docs/assets/sc/2015-07-06-093147_1438x1064_scrot.png
docs/docs/assets/sc/2015-07-06-093152_1438x1064_scrot.png
docs/docs/assets/sc/2015-07-06-093215_1438x1064_scrot.png
docs/docs/assets/sc/2015-07-06-093234_1438x1064_scrot.png
goodies/apache.conf
goodies/gen-dev-conf.sh
goodies/init-debian
goodies/lighttpd.conf
goodies/nginx-fastcgi.conf
goodies/nginx.conf
goodies/tag.sh
ldapcherry/__init__.py
ldapcherry/attributes.py
ldapcherry/cli.py
ldapcherry/exceptions.py
ldapcherry/lclogging.py
ldapcherry/pyyamlwrapper.py
ldapcherry/roles.py
ldapcherry/version.py
ldapcherry.egg-info/PKG-INFO
ldapcherry.egg-info/SOURCES.txt
ldapcherry.egg-info/dependency_links.txt
ldapcherry.egg-info/entry_points.txt
ldapcherry.egg-info/not-zip-safe
ldapcherry.egg-info/requires.txt
ldapcherry.egg-info/top_level.txt
