Metadata-Version: 1.1
Name: ldapcherry
Version: 1.1.1
Summary: A simple web application to manage Ldap entries
Home-page: https://github.com/kakwa/ldapcherry
Author: Pierre-Francois Carpentier
Author-email: carpentier.pf@gmail.com
License: The MIT License (MIT)
